{
  "title": "Установка стека LAMP на операционную систему CentOS 7.6",
  "pageDescription": "",
  "shortDescription": "",
  "metaTitle": "Установка стека LAMP на операционную систему CentOS 7.6",
  "metaDescription": "Стек LAMP включает в себя операционную систему семейства Linux, веб-сервер Apache, систему управления базами данных MySQL и серверный язык сценариев для об",
  "sectionTitle": "Установка стека LAMP на операционную систему CentOS 7.6",
  "markdown": "",
  "icon": "",
  "infobarItems": null,
  "weight": 4,
  "uuid": "f82769fb-0dbb-4c81-a4a5-f4ef57b8e804",
  "createdAt": "2022-03-26T14:10:44.000Z",
  "updatedAt": "2023-08-24T17:46:20.000Z"
}