{
  "title": "Кластерлердің аудит саясаты",
  "shortDescription": "Екінші буын кластерлерінің аудит саясаты қалай құрылған",
  "metaDescription": "Cloud Audit аудит журналына кластер API-інің қандай оқиғалары және қандай көлемде жазылатынын анықтайтын саясат файлының, аудит деңгейлерінің және ережелердің сипаттамасы. Саясат ережелері мен аудит егжей-тегжейлілік деңгейлері қалай бапталатынын біліңіз",
  "sectionTitle": "Кластерлердің аудит саясаты",
  "icon": "",
  "weight": 13,
  "build": {
    "for": [
      "public",
      "private",
      "private-pg",
      "private-pdf",
      "private-pg-pdf",
      "private-cert"
    ]
  },
  "uuid": "9ccc2825-2f25-4f61-889c-fdcfd9b276cc"
}