{
    "title": "Регистрация в VK Cloud",
    "pageDescription": "Создание учетной записи в личном кабинете VK Cloud, подтверждение аккаунта, настройка проекта, активация доступа по API.",
    "shortDescription": "Создание учетной записи в личном кабинете платформы, подтверждение аккаунта, настройка проекта, активация доступа по API",
    "metaTitle": "Регистрация в VK Cloud",
    "metaDescription": "VK Cloud: создание учетной записи в личном кабинете платформы, подтверждение аккаунта, настройка проекта, активация доступа по API",
    "sectionTitle": "Регистрация в VK Cloud",
    "icon": "",
    "weight": 2,
    "additionalUuids": [
        "0229974e-c0aa-46d3-8c6b-2b41b8c12bb4",
        "48b35b2c-c63f-4ba5-91d4-10cd5c06833d",
        "a92c50e0-701c-4aca-869e-0bd73370d7bd",
        "58f18d3d-84c1-4d04-92c6-3903f66976b7"
    ],
    "uuid": "19554fd7-6cdf-4081-aba3-33807f4ea879",
    "createdAt": "2023-02-07T17:15:50.000Z",
    "updatedAt": "2024-08-09T11:12:14.000Z"
}