{
  "title": "Тарифтеу",
  "shortDescription": "Сервисті пайдалану құнын есептеу, бірінші қолданбаға арналған сынақ кезеңі",
  "metaDescription": "VK Cloud ішіндегі 1С:ДЖО сервисінің құны туралы толық ақпарат: баға қалай есептеледі, сынақ кезеңі, төлем, баланс және құжаттар. 1С бұлтты шешімдерін VK Cloud ішінде пайдалану тарифтері мен шарттары туралы білу керек нәрсенің бәрі",
  "sectionTitle": "Тарифтеу",
  "icon": "",
  "weight": 3,
  "build": {
    "for": [
      "public"
    ]
  },
  "uuid": "99e469da-7030-40ed-bb79-78f83b10654d"
}