{
  "title": "Недозагруженные узлы не удаляются при автоматическом масштабировании",
  "shortDescription": "Что делать, если при автоматическом масштабировании не удаляются недозагруженные узлы",
  "metaDescription": "Почему узлы кластера Kubernetes не удаляются автоматически, даже если они недозагружены. Подробные инструкции по анализу и устранению проблем, связанных с PodDisruptionBudget, системными подами, отсутствием контроллера рабочей нагрузки, аннотациями и временем простоя",
  "sectionTitle": "Недозагруженные узлы не удаляются при автоматическом масштабировании",
  "icon": "",
  "weight": 7,
  "uuid": "e2242d3a-2f68-482e-b4be-265764a8229d"
}