{
  "title": "Қадамдық нұсқаулықтар",
  "shortDescription": "Жеке кабинетте сервистерді қосу және сервис инстанстарын басқару",
  "metaDescription": "Marketplace VK Cloud: SaaS және image-based сервистерін басқаруға арналған стандартты операциялар",
  "sectionTitle": "Қадамдық нұсқаулықтар",
  "icon": "",
  "weight": 3,
  "build": {
    "for": [
      "public",
      "private",
      "private-pg",
      "private-pdf",
      "private-pg-pdf",
      "private-cert",
      "s3",
      "s3-pdf",
      "data-p",
      "data-p-pdf"
    ]
  },
  "uuid": "6162e114-93f9-4722-9a5f-a16085a3f590"
}