{
  "title": "Управление кластером",
  "pageDescription": "Пошаговые инструкции по управлению развернутым кластером аналитической базы данных в VK Cloud.",
  "shortDescription": "Масштабирование ресурсов кластера и удаление кластера ADB",
  "metaTitle": "Управление кластером",
  "metaDescription": "ADB VK Cloud: инструкции по управлению развернутым кластером",
  "sectionTitle": "Управление кластером",
  "icon": "",
  "infobarItems": null,
  "weight": 2,
  "uuid": "fdac5b9a-948f-4416-9a1d-86b135843d69",
  "createdAt": "2022-03-26T14:10:44.000Z",
  "updatedAt": "2023-09-08T12:10:50.000Z"
}