{
  "title": "Bitwarden орналастыру",
  "shortDescription": "Тіркелгі деректері мен құпияларды қауіпсіз сақтау және оларды бірлесіп басқару мүмкіндігі бар Bitwarden орналастыру",
  "metaDescription": "Тіркелгі деректері мен құпияларды қауіпсіз сақтау және оларды бірлесіп басқару үшін Bitwarden орналастыру",
  "sectionTitle": "Bitwarden орналастыру",
  "icon": "",
  "weight": 21,
  "build": {
    "for": [
      "public",
      "private",
      "private-pg",
      "private-pdf",
      "private-pg-pdf",
      "private-cert",
      "s3",
      "s3-pdf",
      "data-p",
      "data-p-pdf"
    ]
  },
  "uuid": "7085a8cf-c7a7-4df6-a029-47d1041b8fd0"
}