{
  "title": "Совместимость kubedb с VK Cloud k8saas",
  "pageDescription": "",
  "shortDescription": "",
  "metaTitle": "Совместимость kubedb с VK Cloud k8saas - VK Cloud",
  "metaDescription": "Проблема Проблема масштабирования k8aas с использованием kubedb и команды: 1Resource CREATE failed: WaitConditionTimeout: resources[37].resources.minion_wa",
  "sectionTitle": "Совместимость kubedb с VK Cloud k8saas",
  "markdown": "",
  "icon": "",
  "infobarItems": null,
  "weight": 2,
  "uuid": "5e00ff2e-4f0e-4241-9432-01e820561e76"
}