{
  "title": "Включение множества очередей (multiqueue)",
  "sectionTitle": "Включение множества очередей (multiqueue)",
  "metaTitle": "Включение множества очередей (multiqueue)",
  "pageDescription": "Включение множества очередей (multiqueue).",
  "shortDescription": "Как настроить функциональность multiqueue для повышения производительности сети",
  "metaDescription": "Включение множества очередей (multiqueue)",
  "markdown": "Включение множества очередей (multiqueue).",
  "icon": "",
  "infobarItems": null,
  "weight": 4,
  "uuid": "ea236dda-40ac-4e59-8908-74d1714074c8",
  "createdAt": "2023-04-13T15:57:13.000Z",
  "updatedAt": "2023-08-02T10:07:13.000Z"
}