{
  "title": "Установка SSL-сертификатов на инстансы сервисов",
  "shortDescription": "Система автоматического управления SSL-сертификатами на инстансах сервисов поставщиков",
  "metaDescription": "Система управления SSL-сертификатами на инстансах сервисов поставщиков: автоматическое создание SSL-сертификатов, их установка, настройка прав доступа, обновление с последующим выполнение пользовательских скриптов.",
  "sectionTitle": "Установка SSL-сертификатов на инстансы сервисов",
  "icon": "",
  "weight": 2,
  "uuid": "c12a3eca-4404-43ef-8f95-77c8679be0de"
}