{
  "title": "Тарификация",
  "shortDescription": "Сервис тарификациясының ерекшеліктері және құнды есептеу",
  "metaDescription": "Marketplace VK Cloud: сервис тарификациясының ерекшеліктері, құнды есептеу",
  "sectionTitle": "Тарификация",
  "icon": "",
  "weight": 5,
  "build": {
    "for": [
      "public",
      "private",
      "private-pg",
      "private-pdf",
      "private-pg-pdf",
      "private-cert",
      "s3",
      "s3-pdf",
      "data-p",
      "data-p-pdf"
    ]
  },
  "uuid": "f4eebbe5-9e9a-4a86-a43e-50208cfd7a3d"
}