{
    "title": "Руководство пользователя ВРМ (VK)",
    "sectionTitle": "Руководство пользователя ВРМ (VK)",
    "metaTitle": "Руководство пользователя ВРМ (VK)",
    "pageDescription": "Инструкции по подключению и работе с виртуальным рабочим столом с помощью приложения Cloud Desktop Client.",
    "shortDescription": "Инструкции по подключению и работе с виртуальным рабочим столом с помощью приложения Cloud Desktop Client",
    "metaDescription": "Инструкции по подключению и работе с виртуальным рабочим столом с помощью приложения Cloud Desktop Client",
    "icon": "",
    "weight": 0
}