{
  "title": "Тарифтік жоспар параметрлері",
  "shortDescription": "SaaS-қосымшасының тарифтік жоспарларының базалық параметрлерінің сипаттамасы",
  "metaDescription": "SaaS-қосымшасы конфигурациясының JSON-файлындағы тарифтік жоспар параметрлері: параметр атауы, қысқаша сипаттамасы, форматы, конфигурацияда параметрді көрсету міндеттілігі, әдепкі мәні.",
  "sectionTitle": "Тарифтік жоспар параметрлері",
  "weight": 2,
  "build": {
    "for": [
      "public"
    ]
  },
  "uuid": "41a9d49c-22af-431f-8866-2bedf4e4e24a"
}