{
  "title": "About platform",
  "pageDescription": "Additional information about the VK Cloud Solutions platform.",
  "shortDescription": "Additional information about the VK Cloud Solutions platform",
  "metaTitle": "About platform - VK Cloud Solutions",
  "metaDescription": "Additional information about the VK Cloud Solutions platform",
  "sectionTitle": "About Platform",
  "markdown": "Additional information about the VK Cloud Solutions platform.",
  "icon": "",
  "weight": 5,
  "infobarItems": null,
  "uuid": "92ce5e0e-079f-4525-9570-5a97405ce951"
}