{
  "title": "Быстрое создание ВМ",
  "pageDescription": "",
  "shortDescription": "Быстрое создание виртуальной машины с предустановленной ОС",
  "metaTitle": "Быстрое создание ВМ - VK Cloud Solutions",
  "metaDescription": "Сервис Облачные вычисления обладает широким функционалом, благодаря которому можно создавать и управлять масштабируемыми виртуальными машинами.",
  "sectionTitle": "Быстрое создание ВМ",
  "markdown": "",
  "icon": "",
  "infobarItems": null,
  "weight": 0,
  "uuid": "fb0302a1-b34c-4cd6-be42-4c8a25de630a"
}