{
  "title": "Installing the FAMP stack on a FreeBSD 10.3 operating system",
  "pageDescription": "",
  "shortDescription": "",
  "metaTitle": "Installing the FAMP stack on FreeBSD 10.3",
  "metaDescription": "This article describes how to install a FAMP stack on a Unix family operating system - FreeBSD 10.3. The FAMP stack includes the FreeBSD operating system,",
  "sectionTitle": "Installing the FAMP stack on a FreeBSD 10.3 operating system",
  "markdown": "",
  "icon": "",
  "infobarItems": null,
  "weight": 0,
  "uuid": "d3b49d6c-dbc7-4916-8c80-809d14c28216",
  "createdAt": "2022-03-26T14:10:44.000Z",
  "updatedAt": "2023-08-02T08:33:55.000Z"
}