{
  "title": "Қолмен резервтік көшіру",
  "shortDescription": "Velero көмегімен Kubernetes кластері ресурстарының резервтік көшірмесін жасау мен қалпына келтіруді қолмен қалай пайдалану керек",
  "metaDescription": "Velero көмегімен Kubernetes кластерінің резервтік көшірмесін жасау және қалпына келтіру: резервтік көшірме жасау, қосымшаның істен шығуын имитациялау, ресурстарды қалпына келтіру",
  "sectionTitle": "Қолмен резервтік көшіру",
  "icon": "",
  "weight": 1,
  "build": {
    "for": [
      "public",
      "private",
      "private-pg",
      "private-pdf",
      "private-pg-pdf",
      "private-cert"
    ]
  }
}