{
  "title": "Серіктестік бағдарламасы туралы",
  "shortDescription": "VK Cloud серіктестік бағдарламасының мүмкіндіктері мен артықшылықтары",
  "metaDescription": "Бізбен бірге бизнесіңізді дамытып, табыс табыңыз!",
  "sectionTitle": "Серіктестік бағдарламасы туралы",
  "icon": "",
  "disableGithub": true,
  "weight": 0,
  "build": {
    "for": [
      "public",
      "private",
      "private-pg",
      "private-pdf",
      "private-pg-pdf",
      "private-cert",
      "s3",
      "s3-pdf",
      "data-p",
      "data-p-pdf"
    ]
  }
}
