{
  "title": "Создание кластера Kafka + NiFi",
  "pageDescription": "Инструкция по подключению.",
  "shortDescription": "Инструкции по работе с Cloud Streams в VK Cloud",
  "metaTitle": "Создание кластера Kafka + NiFi",
  "metaDescription": "Создание кластера Kafka + NiFi",
  "sectionTitle": "Создание кластера Kafka + NiFi",
  "markdown": "",
  "icon": "",
  "infobarItems": null,
  "weight": 0,
  "uuid": "15f99f51-c59e-4da5-9a1e-a7565cfe8336",
  "createdAt": "2023-05-31T09:51:29.000Z",
  "updatedAt": "2023-07-31T07:16:17.000Z"
}