{
  "title": "Создание ключевой пары",
  "pageDescription": "Описание процесса создания ключевой пары для SSH подключения.",
  "shortDescription": "Процесс создания ключевой пары для SSH подключения",
  "metaTitle": "Создание ключевой пары - VK Cloud",
  "metaDescription": "Процесс создания ключевой пары для SSH подключения",
  "sectionTitle": "Создание ключевой пары",
  "markdown": "Описание процесса создания ключевой пары для SSH подключения.",
  "icon": "",
  "weight": 0,
  "infobarItems": null,
  "uuid": "e7b447ad-858b-4f35-bcbf-e64363907738"
}