{
  "title": "Установка Local DNS Cache",
  "pageDescription": "Установка Local DNS Cache",
  "shortDescription": "Установка Local DNS Cache",
  "metaTitle": "Установка Local DNS Cache - VK Cloud Solutions",
  "metaDescription": "Установка Local DNS Cache позволяет снизить количество запросов в CoreDNS и повысить стабильность преобразования DNS имен.",
  "sectionTitle": "Установка Local DNS Cache",
  "markdown": "",
  "icon": "",
  "infobarItems": null,
  "weight": 3,
  "uuid": "312af785-6883-4587-b9ae-bb2a4b14c533"
}