{
  "title": "Регистрация в VK Cloud",
  "pageDescription": "Создание учетной записи в личном кабинете платформы, активация доступа по API.",
  "shortDescription": "Создание учетной записи в личном кабинете платформы, активация доступа по API",
  "metaTitle": "Регистрация в VK Cloud — VK Cloud",
  "metaDescription": "Создание учетной записи в личном кабинете платформы, активация доступа по API",
  "sectionTitle": "Регистрация в VK Cloud",
  "markdown": "",
  "icon": "",
  "infobarItems": null,
  "weight": 0,
  "uuid": "19554fd7-6cdf-4081-aba3-33807f4ea879"
}