{
    "title": "About service",
    "pageDescription": "Brief description and opportunities of the CDN VK Cloud service",
    "shortDescription": "Brief description and opportunities of the CDN VK Cloud service",
    "metaTitle": "About service",
    "metaDescription": "Description CDN stands for Content-Delivery Network and is a geographically distributed network infrastructure that optimizes the delivery and distribution",
    "sectionTitle": "About service",
    "icon": "",
    "weight": 0,
    "uuid": "54ed68ba-31ab-402a-8769-02351d939a84",
    "createdAt": "2022-03-26T14:10:44.000Z",
    "updatedAt": "2024-08-07T15:24:48.000Z"
}