{
  "title": "Көпаймақты сақтау кластарын пайдалану",
  "shortDescription": "Жұмыс жүктемесін тарату үшін көпаймақты сақтау кластарын пайдалану жолы",
  "metaDescription": "Подпен бірдей қолжетімділік аймағында тұрақты томдарды (PV) динамикалық жасау үшін Kubernetes-та көпаймақты сақтау кластарын пайдаланыңыз. StorageClass қалай бапталатынын, қолданбаны қалай орналастыру керектігін және кластердің істен шығуға төзімділігі мен жоғары қолжетімділігін арттыру үшін PV-лердің аймақтар арасында дұрыс бөлінуін қалай тексеруге болатынын біліңіз.",
  "sectionTitle": "Көпаймақты сақтау кластарын пайдалану",
  "icon": "",
  "weight": 8,
  "uuid": "",
  "build": {
    "for": [
      "public",
      "private",
      "private-pg",
      "private-pdf",
      "private-pg-pdf",
      "private-cert"
    ]
  }
}
