{
  "title": "Политика конфиденциальности платформы «VK Cloud»",
  "pageDescription": "",
  "shortDescription": "",
  "metaTitle": "Политика конфиденциальности платформы «VK Cloud»",
  "metaDescription": "1. Предметом регулирования настоящей Политики конфиденциальности (далее – «Политика») являются отношения между Обществом с ограниченной ответственностью «ВК»",
  "sectionTitle": "Политика конфиденциальности платформы «VK Cloud»",
  "markdown": "",
  "icon": "",
  "infobarItems": null,
  "disableGithub": true,
  "disableDateInformation": true,
  "weight": 5,
  "uuid": "2dffd262-7661-4438-828f-d4134e29c461",
  "createdAt": "2022-03-26T14:10:44.000Z",
  "updatedAt": "2023-09-13T07:36:33.000Z"
}