{
  "title": "Объектілер мен бакеттерді басқару мүмкіндіктері",
  "shortDescription": "Стандартты және көпбөлікті жүктеу, объектілерді көшіру және сервистің басқа мүмкіндіктері",
  "metaDescription": "VK Object Storage деректерін басқару мүмкіндіктері: өлшем шектеулері мен multipart артықшылықтары бар стандартты және көпбөлікті (multipart) жүктеу, объектілерді көшіру (бакет ішінде және бакеттер арасында), бакеттегі оқиғалар туралы хабарландырулар (жүктеу, жою, көшіру және т.б.), объектілерді тегтеу, сондай-ақ S3 API пайдалану",
  "sectionTitle": "Объектілер мен бакеттерді басқару мүмкіндіктері",
  "icon": "",
  "weight": 2
}