{
  "title": "Пул рабочих столов",
  "pageDescription": "Пул рабочих столов — это объединение нескольких рабочих столов, которые используют общие вычислительные ресурсы. Рабочие столы не могут быть созданы без пула.",
  "shortDescription": "Создание пула рабочих столов и управление им",
  "metaTitle": "Пул рабочих столов",
  "metaDescription": "Объединение рабочих столов в едином пуле ресурсов.",
  "sectionTitle": "Пул рабочих столов",
  "markdown": "Пул рабочих столов — это объединение нескольких рабочих столов, которые используют общие вычислительные ресурсы. Рабочие столы не могут быть созданы без пула.",
  "icon": "",
  "infobarItems": null,
  "weight": 2
}