{
  "title": "Міндетті белгілерді баптау",
  "shortDescription": "Міндетті белгілердің болуын талап ететін Gatekeeper шектеуін қалай жасауға болады",
  "metaDescription": "VK Cloud-та жасалатын Kubernetes ресурстарында міндетті белгілердің болуын талап ететін Gatekeeper шектеуін қалай жасауға болатынын біліңіз",
  "sectionTitle": "Міндетті белгілерді баптау",
  "icon": "",
  "weight": 1,
  "build": {
    "for": [
      "public",
      "private",
      "private-pg",
      "private-pdf",
      "private-pg-pdf",
      "private-cert"
    ]
  },
  "uuid": "67fb6453-192f-4fc2-8f4a-c22aba447232"
}