{
    "title": "Payment, refund, bonuses",
    "pageDescription": "View VK Cloud balance, payment control, refund, how to get welcome bonuses.",
    "shortDescription": "Balance view, payment control, refund, how to get welcome bonuses",
    "metaTitle": "Payment, refund, bonuses",
    "metaDescription": "VK Cloud: balance view, payment control, refund, how to get welcome bonuses",
    "sectionTitle": "Payment, refund, bonuses",
    "icon": "",
    "infobarItems": null,
    "weight": 1,
    "uuid": "2ddfa1a4-ec01-4868-b0fd-4dcecdccc07f",
    "createdAt": "2023-11-27T13:21:45.000Z",
    "updatedAt": "2024-02-01T07:07:52.000Z"
}