{
  "title": "Idea Portal",
  "pageDescription": "Submit and view suggestions for improving the VK Cloud platform.",
  "shortDescription": "Submit and view suggestions to improve the VK Cloud platform",
  "metaTitle": "Ideas Portal",
  "metaDescription": "Submit and view suggestions to improve the VK Cloud platform",
  "sectionTitle": "Ideas Portal",
  "markdown": "Submit and view suggestions to improve the VK Cloud platform.",
  "icon": "",
  "weight": 3,
  "infobarItems": null,
  "uuid": "7153a6a3-19af-4a7d-906c-dd88aad569a8"
}