{
  "title": "Data Platform UI Console",
  "pageDescription": "Сервис для упрощения работы с платформой данных в инфраструктуре VK Cloud.",
  "shortDescription": "Сервис для упрощения работы с платформой данных в инфраструктуре VK Cloud",
  "metaTitle": "Data Platform UI Console",
  "metaDescription": "Сервис для упрощения работы с платформой данных в инфраструктуре VK Cloud",
  "sectionTitle": "Data Platform UI Console",
  "icon": "",
  "weight": 500,
  "isBeta": true,
  "uuid": "58eb5560-944a-4887-8699-f1a7dfc08a28"
}